jsontoggle/__init__.py
jsontoggle/jsontoggle_core.py
jsontoggle-0.1.2.dist-info/METADATA
jsontoggle-0.1.2.dist-info/WHEEL
jsontoggle-0.1.2.dist-info/entry_points.txt
jsontoggle-0.1.2.dist-info/top_level.txt
jsontoggle-0.1.2.dist-info/RECORD
