Metadata-Version: 2.4
Name: jsontoggle
Version: 0.1.2
Summary: A CLI tool for toggling JSON nodes.
Author-email: Crush <crush@charm.land>
Requires-Python: >=3.8
Requires-Dist: pydash>=8.0.5
Requires-Dist: textual>=0.61.0
Requires-Dist: click>=8.1.7
